doxygenwhere/__init__.py
doxygenwhere/data/doxygen-1.9.5.windows.x64.bin.zip
doxygenwhere-1.6.0.dist-info/LICENSE
doxygenwhere-1.6.0.dist-info/METADATA
doxygenwhere-1.6.0.dist-info/WHEEL
doxygenwhere-1.6.0.dist-info/top_level.txt
doxygenwhere-1.6.0.dist-info/RECORD
