Metadata-Version: 2.1
Name: doxygenwhere
Version: 1.6.0
Summary: Python interface to locate doxygen installation
Home-page: https://github.com/bjoernrennfanz/pydoxygenwhere
Author: Björn Rennfanz
Author-email: bjoern@fam-rennfanz.de
License: MIT
Classifier: License :: OSI Approved :: MIT License
Classifier: Operating System :: Microsoft :: Windows
Classifier: Programming Language :: Python :: 2.7
Classifier: Programming Language :: Python :: 3
License-File: LICENSE
